{"about-ci-cd.md":"TXmBhuJv","account-removal.md":"CqZQnZTZ","api_authentication.md":"rayqdVft","api_backup-destinations.md":"B-sru6_O","api_backup-task-logs.md":"Pc0jc4xQ","api_backup-tasks.md":"_PtI6SsN","api_introduction.md":"T9AV5svF","api_notification-streams.md":"TUBnAcEt","api_remote-servers.md":"V5AWZXla","api_tags.md":"CosjzB96","api_user.md":"C6mw2vea","backup-destinations.md":"Cw4yIjyr","backup-tasks.md":"DRqQYknw","bumping-the-version.md":"D-t_8QzD","commands.md":"CBAXPlUi","development-handbook.md":"BR_G59hT","frequently-asked-questions.md":"Dz3uj0UD","index.md":"DpK2EmqQ","installation.md":"ekwNMyiD","notification-streams.md":"Ed5y_8oH","remote-servers.md":"CU6ea3pe","tags.md":"Cn-uWnsq","version.md":"Cb-91vnk","your-profile.md":"Dsq9cQ30"}
